{
  "ok": true,
  "generatedAt": "2026-07-05T16:17:58.590Z",
  "timezone": "Asia/Ho_Chi_Minh",
  "summary": {
    "todayVisitors": 129,
    "todayPageViews": 138,
    "todayRequests": 287,
    "last24hVisitors": 137,
    "last24hPageViews": 149,
    "last24hRequests": 316
  },
  "hourly": [
    {
      "time": "2026-07-04T17:00:00Z",
      "visitors": 3,
      "requests": 4
    },
    {
      "time": "2026-07-04T18:00:00Z",
      "visitors": 3,
      "requests": 3
    },
    {
      "time": "2026-07-04T20:00:00Z",
      "visitors": 11,
      "requests": 19
    },
    {
      "time": "2026-07-04T23:00:00Z",
      "visitors": 2,
      "requests": 3
    },
    {
      "time": "2026-07-05T01:00:00Z",
      "visitors": 55,
      "requests": 81
    },
    {
      "time": "2026-07-05T02:00:00Z",
      "visitors": 19,
      "requests": 27
    },
    {
      "time": "2026-07-05T03:00:00Z",
      "visitors": 9,
      "requests": 34
    },
    {
      "time": "2026-07-05T04:00:00Z",
      "visitors": 7,
      "requests": 16
    },
    {
      "time": "2026-07-05T05:00:00Z",
      "visitors": 10,
      "requests": 18
    },
    {
      "time": "2026-07-05T06:00:00Z",
      "visitors": 8,
      "requests": 25
    },
    {
      "time": "2026-07-05T07:00:00Z",
      "visitors": 8,
      "requests": 14
    },
    {
      "time": "2026-07-05T08:00:00Z",
      "visitors": 7,
      "requests": 8
    },
    {
      "time": "2026-07-05T09:00:00Z",
      "visitors": 1,
      "requests": 1
    },
    {
      "time": "2026-07-05T10:00:00Z",
      "visitors": 3,
      "requests": 13
    },
    {
      "time": "2026-07-05T11:00:00Z",
      "visitors": 3,
      "requests": 6
    },
    {
      "time": "2026-07-05T12:00:00Z",
      "visitors": 5,
      "requests": 6
    },
    {
      "time": "2026-07-05T13:00:00Z",
      "visitors": 15,
      "requests": 25
    },
    {
      "time": "2026-07-05T14:00:00Z",
      "visitors": 4,
      "requests": 11
    },
    {
      "time": "2026-07-05T15:00:00Z",
      "visitors": 2,
      "requests": 2
    }
  ],
  "daily": [
    {
      "date": "2026-06-29",
      "visitors": 148,
      "pageViews": 208,
      "requests": 424
    },
    {
      "date": "2026-06-30",
      "visitors": 128,
      "pageViews": 211,
      "requests": 587
    },
    {
      "date": "2026-07-01",
      "visitors": 150,
      "pageViews": 405,
      "requests": 621
    },
    {
      "date": "2026-07-02",
      "visitors": 151,
      "pageViews": 177,
      "requests": 408
    },
    {
      "date": "2026-07-03",
      "visitors": 166,
      "pageViews": 302,
      "requests": 757
    },
    {
      "date": "2026-07-04",
      "visitors": 147,
      "pageViews": 175,
      "requests": 424
    },
    {
      "date": "2026-07-05",
      "visitors": 129,
      "pageViews": 138,
      "requests": 287
    }
  ],
  "topPages": [
    {
      "path": "/vi/tin-tuc/crm-cho-nha-thuoc-bat-dau-tu-dau-lieu-khach-hang/",
      "views": 92
    },
    {
      "path": "/cdn-cgi/rum",
      "views": 45
    },
    {
      "path": "/robots.txt",
      "views": 23
    },
    {
      "path": "/",
      "views": 21
    },
    {
      "path": "/images/logo.png",
      "views": 17
    },
    {
      "path": "/vi/",
      "views": 14
    },
    {
      "path": "/sitemap-index.xml",
      "views": 12
    },
    {
      "path": "/api/stats",
      "views": 12
    },
    {
      "path": "/cdn-cgi/scripts/5c5dd728/cloudflare-static/email-decode.min.js",
      "views": 9
    },
    {
      "path": "/_astro/Footer.D_gZUTcD.css",
      "views": 8
    },
    {
      "path": "/images/tin-tuc/crm-cho-nha-thuoc-bat-dau-tu-dau-lieu-khach-hang.png",
      "views": 8
    },
    {
      "path": "/vi",
      "views": 6
    },
    {
      "path": "/sitemap.xml",
      "views": 6
    },
    {
      "path": "/vi/thong-ke/",
      "views": 6
    },
    {
      "path": "/config.json",
      "views": 4
    }
  ]
}
